pbox/__init__.py
pbox/app.py
pbox/sandbox/__init__.py
pbox/sandbox/manager.py
pbox/sandbox/sand_box.py
pbox/utils/__init__.py
pbox/utils/secret.py
pbox/utils/stdouts.py
pbox/utils/validator.py
PandoraBox-1.2.0.dist-info/METADATA
PandoraBox-1.2.0.dist-info/WHEEL
PandoraBox-1.2.0.dist-info/entry_points.txt
PandoraBox-1.2.0.dist-info/top_level.txt
PandoraBox-1.2.0.dist-info/RECORD
