Metadata-Version: 2.1
Name: PandoraBox
Version: 1.2.0
Summary: Pandora Box Is All You Need. You Can Create Python Environment, Execute Python, Close Python Environment Freely and Easily.
Home-page: https://github.com/pydaxing/PandoraBox
Author: pydaxing
Author-email: pydaxing@gmail.com
Classifier: Development Status :: 5 - Production/Stable
Classifier: Intended Audience :: Developers
Classifier: Programming Language :: Python :: 3
Classifier: Programming Language :: Python :: 3.6
Classifier: Programming Language :: Python :: 3.7
Classifier: Programming Language :: Python :: 3.8
Classifier: Programming Language :: Python :: 3.9
Classifier: Programming Language :: Python :: 3.10
Classifier: Programming Language :: Python :: 3.11
Classifier: License :: OSI Approved :: MIT License
Classifier: Operating System :: OS Independent
Classifier: Topic :: Software Development :: Libraries :: Python Modules
Requires-Python: >=3.6
Requires-Dist: requests
Requires-Dist: anyio
Requires-Dist: h11
Requires-Dist: fastapi
Requires-Dist: uvicorn
Requires-Dist: pydantic
Requires-Dist: jupyter-client
Requires-Dist: ipython
Requires-Dist: ipykernel
Requires-Dist: pandas
Requires-Dist: numpy
Requires-Dist: matplotlib
Requires-Dist: jsonlines
